[
    {
        "name": "John",
        "age": 30,
        "attributes": {
            "str": 5,
            "dex": 14,
            "int": 4
        }
    },
    {
        "name": "Yoo",
        "age": 6,
        "attributes": {
            "str": 34,
            "dex": 15,
            "int": 6
        }
    },
    {
        "name": "Kaith",
        "age": 30,
        "attributes": {
            "str": 20,
            "dex": 18,
            "int": 6
        }
    },
    {
        "name": "Kaith",
        "age": 30,
        "attributes": {
            "str": 21,
            "dex": 6,
            "int": 17
        }
    }
]